README.rst
pyproject.toml
setup.cfg
setup.py
src/FicusFramework.egg-info/PKG-INFO
src/FicusFramework.egg-info/SOURCES.txt
src/FicusFramework.egg-info/dependency_links.txt
src/FicusFramework.egg-info/not-zip-safe
src/FicusFramework.egg-info/requires.txt
src/FicusFramework.egg-info/top_level.txt
src/api/__init__.py
src/api/exceptions.py
src/api/annotation/__init__.py
src/api/annotation/annotation.py
src/api/handler/IAsyncAble.py
src/api/handler/ICacheAble.py
src/api/handler/ICacheAbleHandler.py
src/api/handler/IHandler.py
src/api/handler/IKillable.py
src/api/handler/ILogAbleHandler.py
src/api/handler/IProgressAble.py
src/api/handler/IRevoke.py
src/api/handler/ITaskHandler.py
src/api/handler/__init__.py
src/api/handler/ce/AbstractAsyncServiceBatchCE.py
src/api/handler/ce/AbstractBatchCE.py
src/api/handler/ce/AbstractMessageCE.py
src/api/handler/ce/IMessageCE.py
src/api/handler/ce/ISampleScriptCE.py
src/api/handler/ce/ISimpleScriptCE.py
src/api/handler/ce/__init__.py
src/api/handler/crawl/AbstractBatchCrawl.py
src/api/handler/crawl/AbstractSimpleCrawl.py
src/api/handler/crawl/ISampleScriptCrawl.py
src/api/handler/crawl/ISimpleScriptCrawl.py
src/api/handler/crawl/__init__.py
src/api/handler/message/IMessageHandler.py
src/api/handler/message/__init__.py
src/api/handler/outputer/IBaseOutputer.py
src/api/handler/outputer/IBatchOutputer.py
src/api/handler/outputer/ISimpleOutputer.py
src/api/handler/outputer/__init__.py
src/api/handler/script/ICacheAbleScript.py
src/api/handler/script/IProgressAbleScript.py
src/api/handler/script/ScriptHandlerHolder.py
src/api/handler/script/ScriptPythonFactory.py
src/api/handler/script/ScriptPythonTaskHandler.py
src/api/handler/script/__init__.py
src/api/model/AlgoOutWrapper.py
src/api/model/AlgorithmFdInputWrapper.py
src/api/model/AsyncServiceRequest.py
src/api/model/AsyncServiceResponse.py
src/api/model/BatchOutputPipe.py
src/api/model/Condition.py
src/api/model/FactDatasource.py
src/api/model/FactDatasourceQueryParameter.py
src/api/model/FdInputPipe.py
src/api/model/FdInputWrapper.py
src/api/model/GraphNode.py
src/api/model/GraphRelation.py
src/api/model/MetaModel.py
src/api/model/MetaModelField.py
src/api/model/MetaModelTransform.py
src/api/model/OtherTargetOutputPipe.py
