Metadata-Version: 1.1
Name: FicusFramework
Version: 3.1.2.post2
Summary: A framework for Ficus by Python3. Require Sobey-Ficus:3.0.2304181043+
Home-page: https://git.sobey.com/SobeyHive/FicusFramework4Py
Author: sunxiang0918
Author-email: sunxiang0918@gmail.com
License: MIT
Keywords: ficus framework python
Platform: UNKNOWN
Classifier: Intended Audience :: Developers
Classifier: License :: OSI Approved :: GNU Lesser General Public License v2 or later (LGPLv2+)
Classifier: Natural Language :: Chinese (Simplified)
Classifier: Programming Language :: Python :: 3.6
Classifier: Programming Language :: Python :: 3.7
